tone/__init__.py
tone/utils/__init__.py
tone/utils/attrdict.py
tone/utils/ipython.py
tone/utils/learning.py
tone/utils/logger.py
tone-0.1.0.dist-info/LICENSE
tone-0.1.0.dist-info/METADATA
tone-0.1.0.dist-info/WHEEL
tone-0.1.0.dist-info/top_level.txt
tone-0.1.0.dist-info/zip-safe
tone-0.1.0.dist-info/RECORD
