Metadata-Version: 2.1
Name: tone
Version: 0.1.0
Summary: Deal with tone
Home-page: https://github.com/StevenBaby/tone
Author: StevenKang
Author-email: kangweibaby@163.com
License: MIT
Platform: any
Classifier: License :: OSI Approved :: MIT License
Classifier: Intended Audience :: Developers
Classifier: Operating System :: OS Independent
Classifier: Programming Language :: Python :: 3
License-File: LICENSE
